django_use_email_as_username/__init__.py
django_use_email_as_username/admin.py
django_use_email_as_username/apps.py
django_use_email_as_username/management/commands/app_template/__init__.py-tpl
django_use_email_as_username/management/commands/app_template/admin.py-tpl
django_use_email_as_username/management/commands/app_template/apps.py-tpl
django_use_email_as_username/management/commands/app_template/migrations/__init__.py-tpl
django_use_email_as_username/management/commands/app_template/models.py-tpl
django_use_email_as_username/management/commands/create_custom_user_app.py
django_use_email_as_username/models.py
django_use_email_as_username-1.3.0.dist-info/LICENSE
django_use_email_as_username-1.3.0.dist-info/WHEEL
django_use_email_as_username-1.3.0.dist-info/METADATA
django_use_email_as_username-1.3.0.dist-info/RECORD
