Metadata-Version: 2.1
Name: django-use-email-as-username
Version: 1.3.0
Summary: A Django app to use email as username for user authentication.
Home-page: https://github.com/jmfederico/django-use-email-as-username
License: BSD-3-Clause
Keywords: django,email,auth,username
Author: Federico Jaramillo Martínez
Author-email: federicojaramillom@gmail.com
Requires-Python: >=3.5
Classifier: Development Status :: 5 - Production/Stable
Classifier: Framework :: Django
Classifier: Framework :: Django :: 1.11
Classifier: Framework :: Django :: 2.0
Classifier: Framework :: Django :: 2.1
Classifier: Framework :: Django :: 2.2
Classifier: Framework :: Django :: 3.0
Classifier: Framework :: Django :: 3.1
Classifier: Framework :: Django :: 3.2
Classifier: Framework :: Django :: 4.0
Classifier: Framework :: Django :: 4.1
Classifier: Intended Audience :: Developers
Classifier: License :: OSI Approved :: BSD License
Classifier: Natural Language :: English
Classifier: Programming Language :: Python :: 3
Classifier: Programming Language :: Python :: 3.5
Classifier: Programming Language :: Python :: 3.6
Classifier: Programming Language :: Python :: 3.7
Classifier: Programming Language :: Python :: 3.8
Classifier: Programming Language :: Python :: 3.9
Classifier: Programming Language :: Python :: 3.10
Classifier: Programming Language :: Python :: 3.11
Provides-Extra: testing
Requires-Dist: codecov (>=2.0.15); extra == "testing"
Requires-Dist: coverage (>=4.0); extra == "testing"
Requires-Dist: django (>=1.11)
Project-URL: Repository, https://github.com/jmfederico/django-use-email-as-username
